odoo9_addon_base_custom_info-9.0.2.0.0.99.dev12-py3.8-nspkg.pth
odoo_addons/base_custom_info/README.rst
odoo_addons/base_custom_info/__init__.py
odoo_addons/base_custom_info/__openerp__.py
odoo_addons/base_custom_info/demo/custom.info.category.csv
odoo_addons/base_custom_info/demo/custom.info.option.csv
odoo_addons/base_custom_info/demo/custom.info.property.csv
odoo_addons/base_custom_info/demo/custom.info.template.csv
odoo_addons/base_custom_info/demo/custom_info_property_defaults.yml
odoo_addons/base_custom_info/demo/res_groups.xml
odoo_addons/base_custom_info/i18n/am.po
odoo_addons/base_custom_info/i18n/ar.po
odoo_addons/base_custom_info/i18n/base_custom_info.pot
odoo_addons/base_custom_info/i18n/bg.po
odoo_addons/base_custom_info/i18n/bs.po
odoo_addons/base_custom_info/i18n/ca.po
odoo_addons/base_custom_info/i18n/ca_ES.po
odoo_addons/base_custom_info/i18n/cs.po
odoo_addons/base_custom_info/i18n/da.po
odoo_addons/base_custom_info/i18n/da_DK.po
odoo_addons/base_custom_info/i18n/de.po
odoo_addons/base_custom_info/i18n/el_GR.po
odoo_addons/base_custom_info/i18n/en_GB.po
odoo_addons/base_custom_info/i18n/es.po
odoo_addons/base_custom_info/i18n/es_AR.po
odoo_addons/base_custom_info/i18n/es_CL.po
odoo_addons/base_custom_info/i18n/es_CO.po
odoo_addons/base_custom_info/i18n/es_CR.po
odoo_addons/base_custom_info/i18n/es_DO.po
odoo_addons/base_custom_info/i18n/es_EC.po
odoo_addons/base_custom_info/i18n/es_ES.po
odoo_addons/base_custom_info/i18n/es_MX.po
odoo_addons/base_custom_info/i18n/es_PE.po
odoo_addons/base_custom_info/i18n/es_PY.po
odoo_addons/base_custom_info/i18n/es_VE.po
odoo_addons/base_custom_info/i18n/et.po
odoo_addons/base_custom_info/i18n/eu.po
odoo_addons/base_custom_info/i18n/fa.po
odoo_addons/base_custom_info/i18n/fi.po
odoo_addons/base_custom_info/i18n/fr.po
odoo_addons/base_custom_info/i18n/fr_CA.po
odoo_addons/base_custom_info/i18n/fr_CH.po
odoo_addons/base_custom_info/i18n/gl.po
odoo_addons/base_custom_info/i18n/gl_ES.po
odoo9_addon_base_custom_info-9.0.2.0.0.99.dev12.dist-info/METADATA
odoo9_addon_base_custom_info-9.0.2.0.0.99.dev12.dist-info/WHEEL
odoo9_addon_base_custom_info-9.0.2.0.0.99.dev12.dist-info/namespace_packages.txt
odoo9_addon_base_custom_info-9.0.2.0.0.99.dev12.dist-info/top_level.txt
odoo9_addon_base_custom_info-9.0.2.0.0.99.dev12.dist-info/RECORD
